kdotp_generator/__init__.py
kdotp_generator/_decompose_kp.py
kdotp_generator/_expr_utils.py
kdotp_generator/_linalg.py
kdotp_generator/_logging_setup.py
kdotp_generator/_repr_utils.py
kdotp_generator/_symmetric_hamiltonian.py
kdotp_generator/_to_matrix.py
kdotp_generator/MSG_linear_coir_data/1.1.npy
kdotp_generator/MSG_linear_coir_data/1.2.npy
kdotp_generator/MSG_linear_coir_data/1.3.npy
kdotp_generator/MSG_linear_coir_data/10.42.npy
kdotp_generator/MSG_linear_coir_data/10.43.npy
kdotp_generator/MSG_linear_coir_data/10.44.npy
kdotp_generator/MSG_linear_coir_data/10.45.npy
kdotp_generator/MSG_linear_coir_data/10.46.npy
kdotp_generator/MSG_linear_coir_data/10.47.npy
kdotp_generator/MSG_linear_coir_data/10.48.npy
kdotp_generator/MSG_linear_coir_data/10.49.npy
kdotp_generator/MSG_linear_coir_data/100.171.npy
kdotp_generator/MSG_linear_coir_data/100.172.npy
kdotp_generator/MSG_linear_coir_data/100.173.npy
kdotp_generator/MSG_linear_coir_data/100.174.npy
kdotp_generator/MSG_linear_coir_data/100.175.npy
kdotp_generator/MSG_linear_coir_data/100.176.npy
kdotp_generator/MSG_linear_coir_data/100.177.npy
kdotp_generator/MSG_linear_coir_data/100.178.npy
kdotp_generator/MSG_linear_coir_data/101.179.npy
kdotp_generator/MSG_linear_coir_data/101.180.npy
kdotp_generator/MSG_linear_coir_data/101.181.npy
kdotp_generator/MSG_linear_coir_data/101.182.npy
kdotp_generator/MSG_linear_coir_data/101.183.npy
kdotp_generator/MSG_linear_coir_data/101.184.npy
kdotp_generator/MSG_linear_coir_data/101.185.npy
kdotp_generator/MSG_linear_coir_data/101.186.npy
kdotp_generator/MSG_linear_coir_data/102.187.npy
kdotp_generator/MSG_linear_coir_data/102.188.npy
kdotp_generator/MSG_linear_coir_data/102.189.npy
kdotp_generator/MSG_linear_coir_data/102.190.npy
kdotp_generator/MSG_linear_coir_data/102.191.npy
kdotp_generator/MSG_linear_coir_data/102.192.npy
kdotp_generator/MSG_linear_coir_data/102.193.npy
kdotp_generator/MSG_linear_coir_data/102.194.npy
kdotp_generator/MSG_linear_coir_data/103.195.npy
kdotp_generator-1.0.1.dist-info/LICENSE.txt
kdotp_generator-1.0.1.dist-info/METADATA
kdotp_generator-1.0.1.dist-info/WHEEL
kdotp_generator-1.0.1.dist-info/top_level.txt
kdotp_generator-1.0.1.dist-info/RECORD
